ConvKAN3D/ConvKAN3D.py
ConvKAN3D/__init__.py
ConvKAN3D/efficient_kan.py
ConvKAN3D-0.1.1.dist-info/LICENSE
ConvKAN3D-0.1.1.dist-info/METADATA
ConvKAN3D-0.1.1.dist-info/WHEEL
ConvKAN3D-0.1.1.dist-info/top_level.txt
ConvKAN3D-0.1.1.dist-info/RECORD
