Metadata-Version: 2.1
Name: ConvKAN3D
Version: 0.1.1
Summary: Implementation of 3D convolutional layer with Kolmogorov-Arnold Networks (KANs)
Author-email: Firas Darwish <fbd2014@nyu.edu>
License: GNU GENERAL PUBLIC LICENSE
Project-URL: Homepage, https://github.com/FirasBDarwish/ConvKAN3D
Project-URL: Repository, https://github.com/FirasBDarwish/ConvKAN3D.git
Project-URL: Bug Tracker, https://github.com/FirasBDarwish/ConvKAN3D/issues
Keywords: python,package,build,tutorial
Classifier: Programming Language :: Python :: 3
Classifier: Intended Audience :: Education
Classifier: License :: OSI Approved :: GNU General Public License v3 (GPLv3)
Classifier: Operating System :: OS Independent
Requires-Python: >=3.7
License-File: LICENSE
Requires-Dist: termcolor
Requires-Dist: torch
Requires-Dist: unfoldNd
Provides-Extra: dev
Requires-Dist: pytest ; extra == 'dev'
